co_excitation_gas_modeling/__init__.py
co_excitation_gas_modeling/__main__.py
co_excitation_gas_modeling/Common_Python_Code/__init__.py
co_excitation_gas_modeling/Common_Python_Code/apply_cosmology.py
co_excitation_gas_modeling/Common_Python_Code/fit_line_ratio.py
co_excitation_gas_modeling/Common_Python_Code/read_model_grid.py
co_excitation_gas_modeling/Common_Python_Code/setup_matplotlib.py
co_excitation_gas_modeling/Data_Tables/Liu2020_COexc_model577f_combined_modeled_line_flux_big_table.fits
co_excitation_gas_modeling/Data_Tables/Liu2020_COexc_model577f_combined_modeled_line_flux_big_table.fits.readme.txt
co_excitation_gas_modeling-0.0.1.dist-info/LICENSE.txt
co_excitation_gas_modeling-0.0.1.dist-info/METADATA
co_excitation_gas_modeling-0.0.1.dist-info/WHEEL
co_excitation_gas_modeling-0.0.1.dist-info/top_level.txt
co_excitation_gas_modeling-0.0.1.dist-info/RECORD
