Metadata-Version: 2.1
Name: co-excitation-gas-modeling
Version: 0.0.1
Summary: A Python Package for Galaxy Cold Molecular Gas Density Esimtation from CO Excitation.
Home-page: https://sites.google.com/view/co-excitation-gas-modeling
Author: DLIU
Author-email: dzliu@mpia.de
Maintainer: DLIU
Maintainer-email: dzliu@mpia.de
License: BSD License
Project-URL: Documentation, https://sites.google.com/view/co-excitation-gas-modeling
Keywords: co excitation galaxy molecular gas density temperature
Platform: all
Classifier: Development Status :: 4 - Beta
Classifier: Operating System :: OS Independent
Classifier: Intended Audience :: Developers
Classifier: License :: OSI Approved :: ISC License (ISCL)
Classifier: Programming Language :: Python
Classifier: Programming Language :: Python :: Implementation
Classifier: Programming Language :: Python :: 2
Classifier: Programming Language :: Python :: 2.7
Classifier: Programming Language :: Python :: 3
Classifier: Programming Language :: Python :: 3.4
Classifier: Programming Language :: Python :: 3.5
Classifier: Programming Language :: Python :: 3.6
Classifier: Programming Language :: Python :: 3.7
Classifier: Programming Language :: Python :: 3.8
Classifier: Topic :: Scientific/Engineering :: Astronomy
Requires-Dist: numpy
Requires-Dist: astropy
Requires-Dist: matplotlib
Requires-Dist: funcsigs ; python_version < "3.0"
